agate_remote-0.2.3.dist-info/licenses/AUTHORS.rst
agate_remote-0.2.3.dist-info/licenses/COPYING
agateremote/__init__.py
agateremote/archive.py
agateremote/table_remote.py
agate_remote-0.2.3.dist-info/METADATA
agate_remote-0.2.3.dist-info/WHEEL
agate_remote-0.2.3.dist-info/top_level.txt
agate_remote-0.2.3.dist-info/RECORD
